codalpy/__init__.py
codalpy/codal.py
codalpy/models.py
codalpy/utils/__init__.py
codalpy/utils/cols.py
codalpy/utils/dicts.py
codalpy/utils/fund.py
codalpy/utils/gen_df.py
codalpy/utils/http.py
codalpy/utils/issuer.py
codalpy/utils/query.py
codalpy/utils/utils.py
codalpy-0.4.5.dist-info/licenses/LICENSE.txt
codalpy-0.4.5.dist-info/METADATA
codalpy-0.4.5.dist-info/WHEEL
codalpy-0.4.5.dist-info/top_level.txt
codalpy-0.4.5.dist-info/RECORD
