Metadata-Version: 2.4
Name: codalpy
Version: 0.4.5
Summary: Add your description here
Requires-Python: >=3.12
License-File: LICENSE.txt
Requires-Dist: beautifulsoup4>=4.13.4
Requires-Dist: fastexcel>=0.13.0
Requires-Dist: jdatetime>=5.2.0
Requires-Dist: polars>=1.27.1
Requires-Dist: pyarrow>=19.0.1
Requires-Dist: pydantic>=2.10.6
Requires-Dist: requests>=2.32.3
Requires-Dist: tqdm>=4.67.1
Dynamic: license-file
